cartes/__init__.py
cartes/conftest.py
cartes/core.py
cartes/py.typed
cartes/atlas/__init__.py
cartes/atlas/topo.py
cartes/crs/__init__.py
cartes/crs/info.py
cartes/crs/meta.py
cartes/crs/vega_params.py
cartes/dataviz/__init__.py
cartes/dataviz/matplotlib_style.json
cartes/dataviz/markers/__init__.py
cartes/dataviz/markers/atc_tower.json
cartes/dataviz/markers/helicopter.json
cartes/dataviz/markers/windsock.json
cartes/osm/__init__.py
cartes/osm/nominatim.py
cartes/osm/requests.py
cartes/osm/overpass/__init__.py
cartes/osm/overpass/core.py
cartes/osm/overpass/meta.py
cartes/osm/overpass/query.py
cartes/osm/overpass/relations/__init__.py
cartes/osm/overpass/relations/boundary.py
cartes/osm/overpass/relations/multipolygon.py
cartes/osm/overpass/relations/waterway.py
cartes/tiles/__init__.py
cartes/tiles/cached.py
cartes/tiles/cartocdn.py
cartes/tiles/fastapi.py
cartes/utils/__init__.py
cartes/utils/cache.py
cartes/utils/descriptors.py
cartes/utils/features.py
cartes/utils/geoaxes.py
cartes/utils/geometry.py
cartes/utils/mixins.py
cartes-0.8.4.dist-info/METADATA
cartes-0.8.4.dist-info/WHEEL
cartes-0.8.4.dist-info/entry_points.txt
cartes-0.8.4.dist-info/RECORD
