Metadata-Version: 2.4
Name: cartes
Version: 0.8.4
Summary: A generic toolbox for building maps in Python
Project-URL: Documentation, https://cartes-viz.github.io/
Project-URL: Code, https://github.com/xoolive/cartes/
Project-URL: Issues, https://github.com/xoolive/cartes/issues/
Project-URL: Releases, https://github.com/xoolive/cartes/releases/
Author-email: Xavier Olive <git@xoolive.org>
License-Expression: MIT
Classifier: Development Status :: 4 - Beta
Classifier: Intended Audience :: Information Technology
Classifier: Intended Audience :: Science/Research
Classifier: License :: OSI Approved :: MIT License
Classifier: Programming Language :: Python :: 3.10
Classifier: Programming Language :: Python :: 3.11
Classifier: Programming Language :: Python :: 3.12
Classifier: Programming Language :: Python :: 3.13
Classifier: Topic :: Scientific/Engineering :: Artificial Intelligence
Classifier: Topic :: Scientific/Engineering :: GIS
Classifier: Topic :: Scientific/Engineering :: Information Analysis
Classifier: Topic :: Scientific/Engineering :: Visualization
Classifier: Topic :: Software Development :: Libraries
Classifier: Typing :: Typed
Requires-Python: >=3.10
Requires-Dist: altair>=5.4.1
Requires-Dist: appdirs>=1.4.4
Requires-Dist: beautifulsoup4>=4.12.3
Requires-Dist: cartopy>=0.24.0
Requires-Dist: fastapi>=0.115.0
Requires-Dist: geopandas>=1.0.1
Requires-Dist: httpx[http2]>=0.27.2
Requires-Dist: jsonschema>=4.23.0
Requires-Dist: lxml>=5.3.0
Requires-Dist: matplotlib>=3.9.2
Requires-Dist: nest-asyncio>=1.6.0
Requires-Dist: networkx>=3.2.1
Requires-Dist: numpy>=2.1.2
Requires-Dist: pandas>=2.2.3
Requires-Dist: pyproj>=3.7.0
Requires-Dist: scipy>=1.14.1
Requires-Dist: shapely>=2.0.6
Requires-Dist: tqdm>=4.66.5
Requires-Dist: uvicorn>=0.31.0
